{
  "period": 238,
  "date": "2026/6/7",
  "items": [
    {
      "lang": "中文",
      "downloadUrl": "https://drive.google.com/uc?export=download&id=1umThLKk9ju6EW45cuSDfdJc-N9rjN_IP",
      "imageUrl": "images/中文.png",
      "localFilename": "中文.png"
    },
    {
      "lang": "英文",
      "downloadUrl": "https://drive.google.com/uc?export=download&id=1pYy1JBWrDy5YD0vY4doO2AlPMSdd3Uxr",
      "imageUrl": "images/英文.png",
      "localFilename": "英文.png"
    },
    {
      "lang": "越南",
      "downloadUrl": "https://drive.google.com/uc?export=download&id=1hy20e9py9yn76WznH2NV2ZPkwVS3SZwc",
      "imageUrl": "images/越南.png",
      "localFilename": "越南.png"
    },
    {
      "lang": "泰文",
      "downloadUrl": "https://drive.google.com/uc?export=download&id=1u53AfcLa138Z6pdw2pKSpPfqsIdhdAho",
      "imageUrl": "images/泰文.png",
      "localFilename": "泰文.png"
    },
    {
      "lang": "柬埔寨",
      "downloadUrl": "https://drive.google.com/uc?export=download&id=1XKKz-5AR2I425JlUPigy6igPUMZNKKrQ",
      "imageUrl": "images/柬埔寨.png",
      "localFilename": "柬埔寨.png"
    },
    {
      "lang": "印尼",
      "downloadUrl": "https://drive.google.com/uc?export=download&id=1ll-rY86IeX9eH4HmkevH_RCQHwAq-WPh",
      "imageUrl": "images/印尼.png",
      "localFilename": "印尼.png"
    },
    {
      "lang": "西文",
      "downloadUrl": "https://drive.google.com/uc?export=download&id=1v6utCyo69boIAM_OWCmDiDOAEhMYpDHC",
      "imageUrl": "images/西文.png",
      "localFilename": "西文.png"
    }
  ]
}